<?xml version="1.0" encoding="utf-8" standalone="yes" ?>
<testmodule starttime="2022-11-01 09:33:38" timestamp=" 105.373689" verdicts="2_basic" measurementid="c0a04a57-5344-4ff4-b442-ebe1aa6a29ab">
  <testcase starttime="2022-11-01 09:33:38" timestamp=" 105.373689">
    <teststep timestamp=" 105.373689" level="0" type="user" ident="1" result="pass">Description of teststep Result of the execution of test step (what is returned from the debugger_ functions in py)</teststep>
    <verdict time="2022-11-01 09:33:38" timestamp=" 105.373689" endtime="2022-11-01 09:33:38" endtimestamp=" 105.373689" result="pass" />
    <title>Test case title</title>
    <ident>SW_IT_modulename_0001</ident>
    <description>Purpose of test: \n Requirement Under Test: (SW Architecture Interface/Requirement ID) \n Test Type: Requirement-Based/Interface test \n Fault injection method used: Yes/No \n Resource usage evaluation: Yes/No \n Priority: Yes/No \n Safety relevant: Yes/No \n</description>
  </testcase>
  <verdict time="2022-11-01 09:33:38" timestamp=" 105.373689" endtime="2022-11-01 09:33:38" endtimestamp=" 105.373689" result="pass" />
  <title>template</title>
  <testlogfiles>
  </testlogfiles>
  <engineer>
    <xinfo>
      <name>Windows Login Name</name>
      <description>victor.popina</description>
    </xinfo>
    <info>
      <name>Test Engineer: </name>
      <description>Insert_Name</description>
    </info>
  </engineer>
  <testsetup>
    <xinfo>
      <name>Version</name>
      <description>CANoe.CAN /pro 15.3.89 (SP3)</description>
    </xinfo>
    <xinfo>
      <name>Configuration</name>
      <description>S:\Tools\CANoe\Config\DAIMLER_MMA_INTEGRATION\BODY3_11.cfg</description>
    </xinfo>
    <xinfo>
      <name>Database BODY3 on BODY3</name>
      <description>S:\Tools\CANoe\Config\DAIMLER_MMA_INTEGRATION\RBTM_FL_STAR_3_Ecu_Extract_2021_42a0_AR43.arxml (2022-06-15 14:40:45)</description>
    </xinfo>
    <xinfo>
      <name>Diagnostic Description of RBTMFL174</name>
      <description>V010, en-US, S:\Tools\CANoe\Config\DAIMLER_MMA_INTEGRATION\Databases\RBTMFL174.cdd (04.03.02, 2022-07-07 19:07:56+03:00)</description>
    </xinfo>
    <xinfo>
      <name>Diagnostic Description of RBTMFR174</name>
      <description>V010, en-US, S:\Tools\CANoe\Config\DAIMLER_MMA_INTEGRATION\Databases\RBTMFR174.cdd (04.03.02, 2022-07-07 19:08:06+03:00)</description>
    </xinfo>
    <xinfo>
      <name>Windows Computer Name</name>
      <description>ART-OF-WL3544</description>
    </xinfo>
    <xinfo>
      <name>CAPL DLL FIB_CANOE_DLL</name>
      <description>C:\Projects\DAI_MMA\Phase_02\View_Development\Tools\CANoe\Config\DAIMLER_MMA_INTEGRATION\Includes\HW_Modules\FIB\FIB_CANOE_DLL.dll</description>
    </xinfo>
    <xinfo>
      <name>Nodelayer Module DAG_ZenzefiNodeLayer</name>
      <description>Security Manager ZenZefi Node Layer (Version 2.8.7.0), C:\ProgramData\Vector\Security Manager\DAG\Binaries\ZenzefiNodeLayer\CANoe_13.0.117\Windows-x64\ZenzefiNodeLayer.dll</description>
    </xinfo>
    <xinfo>
      <name>Nodelayer Module SecMgrCANoeClient</name>
      <description>Security Manager CANoe Node Layer Client (Version 2.8.7.0), C:\ProgramData\Vector\Security Manager\General\Binaries\SecMgrCANoeClient\CANoe_13.0.117\Windows-x64\SecMgrCANoeClient.dll</description>
    </xinfo>
    <xinfo>
      <name>Nodelayer Module AsrPDUIL</name>
      <description>CANoe AutoSAR PDU Interaction Layer NL (General OEM) Version 1.85.67 (Jul  1 2021 14:18:47) , C:\Program Files\Vector CANoe 15\Exec64\AsrPDUIL.dll</description>
    </xinfo>
    <xinfo>
      <name>Nodelayer Module AsrNM33</name>
      <description>AsrNM (Version 3.3.72 Windows 64-Bit), C:\Program Files\Vector CANoe 15\Exec64\AsrNM33.dll</description>
    </xinfo>
    <xinfo>
      <name>Nodelayer Module J1939TestServiceLibraryNL</name>
      <description>J1939 Test Service Library for CANoe, Version 15.3.89.0, C:\Program Files\Vector CANoe 15\Exec64\J1939TestServiceLibraryNL.dll</description>
    </xinfo>
    <info>
      <name>Debugger: </name>
      <description>IC5000</description>
    </info>
    <info>
      <name>Power Supply: </name>
      <description>PSW 30-108</description>
    </info>
    <info>
      <name>Mock-up: </name>
      <description>SBE V2.1</description>
    </info>
  </testsetup>
  <hardware name="CAN Channel Interfaces" category="CategoryCANIF">
    <xinfoset type="device">
      <xinfoobject type="device">
      <xinfo key="channel">
        <name>Channel</name>
        <description>1</description>
      </xinfo>
      <xinfo key="device">
        <name>Device</name>
        <description>VN1611</description>
      </xinfo>
      <xinfo key="serialnumber">
        <name>Serial number</name>
        <description>17703</description>
      </xinfo>
      <xinfo key="driverdllversion">
        <name>Driver DLL version</name>
        <description>21.10.20</description>
      </xinfo>
      <xinfo key="driverversion">
        <name>Driver version</name>
        <description>20.30.14</description>
      </xinfo>
      </xinfoobject>
    </xinfoset>
  </hardware>
</testmodule>
<!--footprint="6b3f04f62297b8183b6f622bc44a24c7" version="1"-->
