<?xml version="1.0" encoding="utf-8" standalone="yes" ?>
<testmodule starttime="2023-04-27 12:36:09" timestamp=" 143.097723" verdicts="2_basic" measurementid="aee8b76d-2844-4679-b0c1-56b154c3a4b9">
  <testcase starttime="2023-04-27 12:36:09" timestamp=" 143.097723">
    <teststep timestamp=" 143.097723" level="0" type="user" ident="" result="na">Authentication for single target</teststep>
    <teststep timestamp=" 143.097723" level="0" type="user" ident="Start" result="na">Start Authentication, target: RBTMFL174</teststep>
    <teststep timestamp=" 145.074727" level="0" type="user" ident="Result" result="pass">Authentication has succeeded, </teststep>
    <verdict time="2023-04-27 12:36:09" timestamp=" 143.097723" endtime="2023-04-27 12:36:11" endtimestamp=" 145.074727" result="pass" />
    <title>LocalAuthentication</title>
  </testcase>
  <verdict time="2023-04-27 12:36:09" timestamp=" 143.097723" endtime="2023-04-27 12:36:11" endtimestamp=" 145.074727" result="pass" />
  <title>DAG_Diagnostics_Authentication</title>
  <testlogfiles>
  </testlogfiles>
  <engineer>
    <xinfo>
      <name>Windows Login Name</name>
      <description>g-rbe.electronics</description>
    </xinfo>
  </engineer>
  <testsetup>
    <xinfo>
      <name>Version</name>
      <description>CANoe.ISO11783.J1939.CANopen.CAN /pro 15.4.35 (SP4)</description>
    </xinfo>
    <xinfo>
      <name>Configuration</name>
      <description>S:\Tools\CANoe\Config\DAIMLER_MMA_INTEGRATION\BODY3_11.cfg</description>
    </xinfo>
    <xinfo>
      <name>Database BODY3 on BODY3</name>
      <description>S:\Tools\CANoe\Config\DAIMLER_MMA_INTEGRATION\Databases\RBTM_FL_FR_STAR_3_Ecu_Extract_2022_17a0_AR43.arxml (2023-04-10 12:44:17)</description>
    </xinfo>
    <xinfo>
      <name>Diagnostic Description of RBTMFL174</name>
      <description>V060, en-US, S:\Tools\CANoe\Config\DAIMLER_MMA_INTEGRATION\Databases\RBTMFL174.cdd (05.06.03, 2023-01-19 16:38:19+02:00)</description>
    </xinfo>
    <xinfo>
      <name>Diagnostic Description of RBTMFR174</name>
      <description>V010, en-US, S:\Tools\CANoe\Config\DAIMLER_MMA_INTEGRATION\Databases\RBTMFR174.cdd (05.06.03, 2023-01-19 16:33:01+02:00)</description>
    </xinfo>
    <xinfo>
      <name>Test Module Name</name>
      <description>DAG_Authentication_TestModule</description>
    </xinfo>
    <xinfo>
      <name>Test Module File</name>
      <description>S:\Tools\CANoe\Config\DAIMLER_MMA_INTEGRATION\Security\Authentication\DAG_Authentication_TestModule.xml</description>
    </xinfo>
    <xinfo>
      <name>Last modification of Test Module File</name>
      <description>2022-06-15, 14:34:20</description>
    </xinfo>
    <xinfo>
      <name>Test Module Library (CAPL)</name>
      <description>S:\Tools\CANoe\Config\DAIMLER_MMA_INTEGRATION\Security\Authentication\LocalAuthentication_TestModule.can</description>
    </xinfo>
    <xinfo>
      <name>Windows Computer Name</name>
      <description>ART-LA-WD3145</description>
    </xinfo>
    <xinfo>
      <name>CAPL DLL FIB_CANOE_DLL</name>
      <description>S:\Tools\CANoe\Config\DAIMLER_MMA_INTEGRATION\Includes\HW_Modules\FIB\FIB_CANOE_DLL.dll</description>
    </xinfo>
    <xinfo>
      <name>Nodelayer Module DAG_ZenzefiNodeLayer</name>
      <description>Security Manager ZenZefi Node Layer (DAG) (Version 2.9.25.0), C:\ProgramData\Vector\Security Manager\DAG\Binaries\ZenzefiNodeLayer\CANoe_13.0.117\Windows-x64\ZenzefiNodeLayer.dll</description>
    </xinfo>
    <xinfo>
      <name>Nodelayer Module SecMgrCANoeClient</name>
      <description>Security Manager CANoe Node Layer Client (Version 2.9.25.0), C:\ProgramData\Vector\Security Manager\General\Binaries\SecMgrCANoeClient\CANoe_13.0.117\Windows-x64\SecMgrCANoeClient.dll</description>
    </xinfo>
    <xinfo>
      <name>Nodelayer Module AsrPDUIL</name>
      <description>CANoe AutoSAR PDU Interaction Layer NL (General OEM) Version 1.85.67 (Sep 17 2021 15:13:31) , c:\ProgramData\Vector\AddOn Packages\Vector AddOn\vModules\CANoe_14_0\Exec64\AsrPDUIL.dll</description>
    </xinfo>
    <xinfo>
      <name>Nodelayer Module AsrNM33</name>
      <description>AsrNM (Version 3.3.72 Windows 64-Bit), c:\ProgramData\Vector\AddOn Packages\Vector AddOn\vModules\CANoe_14_0\Exec64\AsrNM33.dll</description>
    </xinfo>
    <xinfo>
      <name>Nodelayer Module J1939TestServiceLibraryNL</name>
      <description>J1939 Test Service Library for CANoe, Version 15.4.35.0, C:\Program Files\Vector CANoe 15\Exec64\J1939TestServiceLibraryNL.dll</description>
    </xinfo>
  </testsetup>
  <hardware name="CAN Channel Interfaces" category="CategoryCANIF">
    <xinfoset type="device">
      <xinfoobject type="device">
      <xinfo key="channel">
        <name>Channel</name>
        <description>1</description>
      </xinfo>
      <xinfo key="device">
        <name>Device</name>
        <description>VN1611</description>
      </xinfo>
      <xinfo key="serialnumber">
        <name>Serial number</name>
        <description>15258</description>
      </xinfo>
      <xinfo key="driverdllversion">
        <name>Driver DLL version</name>
        <description>11.6.12</description>
      </xinfo>
      <xinfo key="driverversion">
        <name>Driver version</name>
        <description>10.9.12</description>
      </xinfo>
      </xinfoobject>
    </xinfoset>
  </hardware>
</testmodule>
<!--footprint="f810ab2e95b82f58a3df021ffb208a68" version="1"-->
